nocto/__init__.py
nocto/environment.py
nocto/filters.py
nocto/main.py
nocto/py.typed
nocto/types.py
nocto/variables.py
nocto-1.1.0.dist-info/LICENSE
nocto-1.1.0.dist-info/METADATA
nocto-1.1.0.dist-info/WHEEL
nocto-1.1.0.dist-info/entry_points.txt
nocto-1.1.0.dist-info/RECORD
