Metadata-Version: 2.1
Name: nocto
Version: 1.1.0
Summary: Simple CLI tool to replace Octopus-style templated variables in file from local environment.
Home-page: https://github.com/ViliamV/nocto
License: MIT
Author: Viliam Valent
Author-email: viliam@valent.email
Requires-Python: >=3.11,<3.12
Classifier: License :: OSI Approved :: MIT License
Classifier: Programming Language :: Python :: 3
Classifier: Programming Language :: Python :: 3.11
Requires-Dist: python-dotenv (>=1.0.0,<2.0.0)
Requires-Dist: typer[all] (>=0.9.0,<0.10.0)
Project-URL: Repository, https://github.com/ViliamV/nocto
